setup.cfg
setup.py
tgext/__init__.py
tgext.minify.egg-info/PKG-INFO
tgext.minify.egg-info/SOURCES.txt
tgext.minify.egg-info/dependency_links.txt
tgext.minify.egg-info/entry_points.txt
tgext.minify.egg-info/namespace_packages.txt
tgext.minify.egg-info/not-zip-safe
tgext.minify.egg-info/requires.txt
tgext.minify.egg-info/top_level.txt
tgext/minify/__init__.py
tgext/minify/middleware.py
tgext/minify/rcssmin.py