Metadata-Version: 1.1
Name: tgext.minify
Version: 0.0.2
Summary: CSS and JS minifier / obfuscator for TurboGears 2
Home-page: http://bitbucket.org/simock85/tgext.minify
Author: Simone Marzola
Author-email: simone.marzola@axant.it
License: MIT
Keywords: turbogears2.extension CSS JS minify obfuscate mangle WSGI
Platform: UNKNOWN
Classifier: Environment :: Web Environment
Classifier: Topic :: Software Development :: Libraries :: Python Modules
Classifier: Framework :: TurboGears
